pluralcode/__init__.py
pluralcode-0.0.1.dist-info/LICENSE
pluralcode-0.0.1.dist-info/METADATA
pluralcode-0.0.1.dist-info/WHEEL
pluralcode-0.0.1.dist-info/top_level.txt
pluralcode-0.0.1.dist-info/RECORD
